src/libjpeg/Makefile.am
src/libjpeg/Makefile.in
src/libjpeg/README
src/libjpeg/aclocal.m4
src/libjpeg/ar-lib
src/libjpeg/cderror.h
src/libjpeg/cdjpeg.c
src/libjpeg/cdjpeg.h
src/libjpeg/change.log
src/libjpeg/cjpeg.1
src/libjpeg/cjpeg.c
src/libjpeg/ckconfig.c
src/libjpeg/coderules.txt
src/libjpeg/compile
src/libjpeg/config.guess
src/libjpeg/config.sub
src/libjpeg/configure
src/libjpeg/configure.ac
src/libjpeg/depcomp
src/libjpeg/djpeg.1
src/libjpeg/djpeg.c
src/libjpeg/example.c
src/libjpeg/filelist.txt
src/libjpeg/install-sh
src/libjpeg/install.txt
src/libjpeg/jaricom.c
src/libjpeg/jcapimin.c
src/libjpeg/jcapistd.c
src/libjpeg/jcarith.c
src/libjpeg/jccoefct.c
src/libjpeg/jccolor.c
src/libjpeg/jcdctmgr.c
src/libjpeg/jchuff.c
src/libjpeg/jcinit.c
src/libjpeg/jcmainct.c
src/libjpeg/jcmarker.c
src/libjpeg/jcmaster.c
src/libjpeg/jcomapi.c
src/libjpeg/jconfig.bcc
src/libjpeg/jconfig.cfg
src/libjpeg/jconfig.dj
src/libjpeg/jconfig.mac
src/libjpeg/jconfig.manx
src/libjpeg/jconfig.mc6
src/libjpeg/jconfig.sas
src/libjpeg/jconfig.st
src/libjpeg/jconfig.txt
src/libjpeg/jconfig.vc
src/libjpeg/jconfig.vms
src/libjpeg/jconfig.wat
src/libjpeg/jcparam.c
src/libjpeg/jcprepct.c
src/libjpeg/jcsample.c
src/libjpeg/jctrans.c
src/libjpeg/jdapimin.c
src/libjpeg/jdapistd.c
src/libjpeg/jdarith.c
src/libjpeg/jdatadst.c
src/libjpeg/jdatasrc.c
src/libjpeg/jdcoefct.c
src/libjpeg/jdcolor.c
src/libjpeg/jdct.h
src/libjpeg/jddctmgr.c
src/libjpeg/jdhuff.c
src/libjpeg/jdinput.c
src/libjpeg/jdmainct.c
src/libjpeg/jdmarker.c
src/libjpeg/jdmaster.c
src/libjpeg/jdmerge.c
src/libjpeg/jdpostct.c
src/libjpeg/jdsample.c
src/libjpeg/jdtrans.c
src/libjpeg/jerror.c
src/libjpeg/jerror.h
src/libjpeg/jfdctflt.c
src/libjpeg/jfdctfst.c
src/libjpeg/jfdctint.c
src/libjpeg/jidctflt.c
src/libjpeg/jidctfst.c
src/libjpeg/jidctint.c
src/libjpeg/jinclude.h
src/libjpeg/jmemansi.c
src/libjpeg/jmemdos.c
src/libjpeg/jmemdosa.asm
src/libjpeg/jmemmac.c
src/libjpeg/jmemmgr.c
src/libjpeg/jmemname.c
src/libjpeg/jmemnobs.c
torchjpeg-0.9.33.dist-info/LICENSE
torchjpeg-0.9.33.dist-info/METADATA
torchjpeg-0.9.33.dist-info/WHEEL
torchjpeg-0.9.33.dist-info/RECORD
