Metadata-Version: 2.1
Name: torchjpeg
Version: 0.9.33
Summary: Utilities for JPEG data access and manipulation in pytorch
Home-page: https://torchjpeg.readthedocs.io
License: MIT
Author: Max Ehrlich
Requires-Python: >=3.10,<4.0
Classifier: Development Status :: 3 - Alpha
Classifier: License :: OSI Approved :: MIT License
Classifier: Operating System :: POSIX :: Linux
Classifier: Programming Language :: C++
Classifier: Programming Language :: Python
Classifier: Programming Language :: Python :: 3
Classifier: Programming Language :: Python :: 3.10
Classifier: Programming Language :: Python :: 3.11
Classifier: Programming Language :: Python :: 3.12
Classifier: Programming Language :: Python :: 3 :: Only
Classifier: Programming Language :: Python :: 3.8
Classifier: Programming Language :: Python :: 3.9
Requires-Dist: Pillow (>=10.4.0)
Requires-Dist: numpy (>=2.1.1)
Requires-Dist: torch (>=2.4.1,<2.4.2)
Requires-Dist: torchvision (>=0.19.1,<0.19.2)
Project-URL: Documentation, https://torchjpeg.readthedocs.io
Project-URL: Repository, https://gitlab.com/torchjpeg/torchjpeg
